{"cameraMode":{"drawMode":0,"name":"Shaded","section":"Shading Mode"},"sceneLighting":true,"audioPlay":false,"sceneViewState":{"showFog":true,"showMaterialUpdate":false,"showSkybox":true,"showFlares":true,"showImageEffects":true,"showParticleSystems":true},"in2DMode":false,"pivot":{"x":-2.1487436294555666,"y":6.6878461837768559,"z":-0.12205184996128082},"rotation":{"x":0.7116349339485169,"y":-0.013292591087520123,"z":0.01346546970307827,"w":0.7022998332977295},"size":0.17577868700027467,"orthographic":false}